noscrypto/Client.py
noscrypto/Server.py
noscrypto/Utils.py
noscrypto/__init__.py
noscrypto/tests/__init__.py
noscrypto/tests/tests.py
noscrypto-0.2.0.dist-info/LICENSE
noscrypto-0.2.0.dist-info/METADATA
noscrypto-0.2.0.dist-info/WHEEL
noscrypto-0.2.0.dist-info/top_level.txt
noscrypto-0.2.0.dist-info/RECORD
