Metadata-Version: 2.1
Name: noscrypto
Version: 0.2.0
Summary: A reverse engineered packet cryptography - encryption and decryption routines to emulate NosTale client or server
Home-page: https://github.com/morsisko/NosCrypto
Author: morsisko
License: MIT
Platform: UNKNOWN
Classifier: License :: OSI Approved :: MIT License
Classifier: Programming Language :: Python
Classifier: Programming Language :: Python :: 3
Classifier: Programming Language :: Python :: 3.7
Classifier: Development Status :: 5 - Production/Stable
Classifier: Intended Audience :: Developers
Classifier: Topic :: Software Development :: Libraries
